Metadata-Version: 2.1
Name: pandas-should
Version: 0.1.0
Summary: pandas extension for asserting
Home-page: https://github.com/momijiame/pandas-should
Author: momijiame
License: Apache License, Version 2.0
Platform: UNKNOWN
Classifier: Development Status :: 4 - Beta
Classifier: Intended Audience :: Science/Research
Classifier: Operating System :: Unix
Classifier: Programming Language :: Python
Classifier: Programming Language :: Python :: 3
Classifier: Programming Language :: Python :: 3.6
Classifier: Programming Language :: Python :: 3.7
Provides-Extra: testing
Provides-Extra: develop
